{
  "2473375": [
    {
      "id": "2473375-80",
      "uri": "https://dadosabertos.camara.leg.br/api/v2/votacoes/2473375-80",
      "data": "2024-12-19",
      "dataHoraRegistro": "2024-12-19T21:06:10",
      "siglaOrgao": "PLEN",
      "uriOrgao": "https://dadosabertos.camara.leg.br/api/v2/orgaos/180",
      "uriEvento": "https://dadosabertos.camara.leg.br/api/v2/eventos/75369",
      "proposicaoObjeto": null,
      "uriProposicaoObjeto": null,
      "descricao": "Aprovada a Redação Final assinada pelo relator, Dep. Isnaldo Bulhões (MDB-AL).",
      "aprovacao": 1
    },
    {
      "id": "2473375-78",
      "uri": "https://dadosabertos.camara.leg.br/api/v2/votacoes/2473375-78",
      "data": "2024-12-19",
      "dataHoraRegistro": "2024-12-19T21:05:40",
      "siglaOrgao": "PLEN",
      "uriOrgao": "https://dadosabertos.camara.leg.br/api/v2/orgaos/180",
      "uriEvento": "https://dadosabertos.camara.leg.br/api/v2/eventos/75369",
      "proposicaoObjeto": null,
      "uriProposicaoObjeto": null,
      "descricao": "Mantido o texto. Sim: 277; Não: 174; Abstenção: 1; Total: 452.",
      "aprovacao": null
    },
    {
      "id": "2473375-59",
      "uri": "https://dadosabertos.camara.leg.br/api/v2/votacoes/2473375-59",
      "data": "2024-12-19",
      "dataHoraRegistro": "2024-12-19T20:51:32",
      "siglaOrgao": "PLEN",
      "uriOrgao": "https://dadosabertos.camara.leg.br/api/v2/orgaos/180",
      "uriEvento": "https://dadosabertos.camara.leg.br/api/v2/eventos/75369",
      "proposicaoObjeto": null,
      "uriProposicaoObjeto": null,
      "descricao": "Aprovada a Subemenda Substitutiva Global ao Projeto de Lei nº 4.614, de 2024, adotada pelo relator da Comissão Especial, ressalvado o destaque. Sim: 264; Não: 209; Total: 473.",
      "aprovacao": 1
    },
    {
      "id": "2473375-53",
      "uri": "https://dadosabertos.camara.leg.br/api/v2/votacoes/2473375-53",
      "data": "2024-12-19",
      "dataHoraRegistro": "2024-12-19T20:15:16",
      "siglaOrgao": "PLEN",
      "uriOrgao": "https://dadosabertos.camara.leg.br/api/v2/orgaos/180",
      "uriEvento": "https://dadosabertos.camara.leg.br/api/v2/eventos/75369",
      "proposicaoObjeto": null,
      "uriProposicaoObjeto": null,
      "descricao": "Aprovado o Requerimento. Sim: 290; Não: 170; Total: 460.",
      "aprovacao": 1
    },
    {
      "id": "2473375-31",
      "uri": "https://dadosabertos.camara.leg.br/api/v2/votacoes/2473375-31",
      "data": "2024-12-04",
      "dataHoraRegistro": "2024-12-04T22:17:26",
      "siglaOrgao": "PLEN",
      "uriOrgao": "https://dadosabertos.camara.leg.br/api/v2/orgaos/180",
      "uriEvento": null,
      "proposicaoObjeto": null,
      "uriProposicaoObjeto": null,
      "descricao": "Alteração do Regime de Tramitação desta proposição em virtude da Aprovação do REQ 4721/2024.",
      "aprovacao": 1
    },
    {
      "id": "2473375-30",
      "uri": "https://dadosabertos.camara.leg.br/api/v2/votacoes/2473375-30",
      "data": "2024-12-04",
      "dataHoraRegistro": "2024-12-04T22:17:26",
      "siglaOrgao": "SECAP(SGM)",
      "uriOrgao": "https://dadosabertos.camara.leg.br/api/v2/orgaos/100001",
      "uriEvento": null,
      "proposicaoObjeto": null,
      "uriProposicaoObjeto": null,
      "descricao": "Realizar o encaminhamento do PL-4614/2024 à CASP (tramitação simultânea), em razão da aprovação de requerimento de urgência.",
      "aprovacao": 1
    },
    {
      "id": "2473375-29",
      "uri": "https://dadosabertos.camara.leg.br/api/v2/votacoes/2473375-29",
      "data": "2024-12-04",
      "dataHoraRegistro": "2024-12-04T22:17:26",
      "siglaOrgao": "SECAP(SGM)",
      "uriOrgao": "https://dadosabertos.camara.leg.br/api/v2/orgaos/100001",
      "uriEvento": null,
      "proposicaoObjeto": null,
      "uriProposicaoObjeto": null,
      "descricao": "Realizar o encaminhamento do PL-4614/2024 à CPASF (tramitação simultânea), em razão da aprovação de requerimento de urgência.",
      "aprovacao": 1
    },
    {
      "id": "2473375-28",
      "uri": "https://dadosabertos.camara.leg.br/api/v2/votacoes/2473375-28",
      "data": "2024-12-04",
      "dataHoraRegistro": "2024-12-04T22:17:26",
      "siglaOrgao": "SECAP(SGM)",
      "uriOrgao": "https://dadosabertos.camara.leg.br/api/v2/orgaos/100001",
      "uriEvento": null,
      "proposicaoObjeto": null,
      "uriProposicaoObjeto": null,
      "descricao": "Realizar o encaminhamento do PL-4614/2024 à CIDOSO (tramitação simultânea), em razão da aprovação de requerimento de urgência.",
      "aprovacao": 1
    },
    {
      "id": "2473375-27",
      "uri": "https://dadosabertos.camara.leg.br/api/v2/votacoes/2473375-27",
      "data": "2024-12-04",
      "dataHoraRegistro": "2024-12-04T22:17:26",
      "siglaOrgao": "SECAP(SGM)",
      "uriOrgao": "https://dadosabertos.camara.leg.br/api/v2/orgaos/100001",
      "uriEvento": null,
      "proposicaoObjeto": null,
      "uriProposicaoObjeto": null,
      "descricao": "Realizar o encaminhamento do PL-4614/2024 à CPD (tramitação simultânea), em razão da aprovação de requerimento de urgência.",
      "aprovacao": 1
    },
    {
      "id": "2473375-26",
      "uri": "https://dadosabertos.camara.leg.br/api/v2/votacoes/2473375-26",
      "data": "2024-12-04",
      "dataHoraRegistro": "2024-12-04T22:17:26",
      "siglaOrgao": "SECAP(SGM)",
      "uriOrgao": "https://dadosabertos.camara.leg.br/api/v2/orgaos/100001",
      "uriEvento": null,
      "proposicaoObjeto": null,
      "uriProposicaoObjeto": null,
      "descricao": "Realizar o encaminhamento do PL-4614/2024 à CFT (tramitação simultânea), em razão da aprovação de requerimento de urgência.",
      "aprovacao": 1
    },
    {
      "id": "2473375-25",
      "uri": "https://dadosabertos.camara.leg.br/api/v2/votacoes/2473375-25",
      "data": "2024-12-04",
      "dataHoraRegistro": "2024-12-04T22:17:26",
      "siglaOrgao": "SECAP(SGM)",
      "uriOrgao": "https://dadosabertos.camara.leg.br/api/v2/orgaos/100001",
      "uriEvento": null,
      "proposicaoObjeto": null,
      "uriProposicaoObjeto": null,
      "descricao": "Realizar o encaminhamento do PL-4614/2024 à CFT (tramitação simultânea), em razão da aprovação de requerimento de urgência.",
      "aprovacao": 1
    },
    {
      "id": "2473375-24",
      "uri": "https://dadosabertos.camara.leg.br/api/v2/votacoes/2473375-24",
      "data": "2024-12-04",
      "dataHoraRegistro": "2024-12-04T22:17:26",
      "siglaOrgao": "SECAP(SGM)",
      "uriOrgao": "https://dadosabertos.camara.leg.br/api/v2/orgaos/100001",
      "uriEvento": null,
      "proposicaoObjeto": null,
      "uriProposicaoObjeto": null,
      "descricao": "Realizar o encaminhamento do PL-4614/2024 à CCJC (tramitação simultânea), em razão da aprovação de requerimento de urgência.",
      "aprovacao": 1
    },
    {
      "id": "2473375-23",
      "uri": "https://dadosabertos.camara.leg.br/api/v2/votacoes/2473375-23",
      "data": "2024-12-04",
      "dataHoraRegistro": "2024-12-04T22:17:26",
      "siglaOrgao": "SECAP(SGM)",
      "uriOrgao": "https://dadosabertos.camara.leg.br/api/v2/orgaos/100001",
      "uriEvento": null,
      "proposicaoObjeto": null,
      "uriProposicaoObjeto": null,
      "descricao": "Realizar o encaminhamento do PL-4614/2024 à CAPADR (tramitação simultânea), em razão da aprovação de requerimento de urgência.",
      "aprovacao": 1
    }
  ],
  "2270800": [
    {
      "id": "2270800-177",
      "uri": "https://dadosabertos.camara.leg.br/api/v2/votacoes/2270800-177",
      "data": "2025-09-17",
      "dataHoraRegistro": "2025-09-17T14:12:20",
      "siglaOrgao": "PLEN",
      "uriOrgao": "https://dadosabertos.camara.leg.br/api/v2/orgaos/180",
      "uriEvento": "https://dadosabertos.camara.leg.br/api/v2/eventos/79266",
      "proposicaoObjeto": null,
      "uriProposicaoObjeto": null,
      "descricao": "Aprovada a Redação Final assinada pelo Relator, Dep. Claudio Cajado (PP/BA).",
      "aprovacao": 1
    },
    {
      "id": "2270800-175",
      "uri": "https://dadosabertos.camara.leg.br/api/v2/votacoes/2270800-175",
      "data": "2025-09-17",
      "dataHoraRegistro": "2025-09-17T14:11:37",
      "siglaOrgao": "PLEN",
      "uriOrgao": "https://dadosabertos.camara.leg.br/api/v2/orgaos/180",
      "uriEvento": "https://dadosabertos.camara.leg.br/api/v2/eventos/79266",
      "proposicaoObjeto": null,
      "uriProposicaoObjeto": null,
      "descricao": "Aprovada a Emenda Aglutinativa de Plenário nº 1. Sim: 314; Não: 168; Total: 482.",
      "aprovacao": 1
    },
    {
      "id": "2270800-172",
      "uri": "https://dadosabertos.camara.leg.br/api/v2/votacoes/2270800-172",
      "data": "2025-09-17",
      "dataHoraRegistro": "2025-09-17T13:13:18",
      "siglaOrgao": "PLEN",
      "uriOrgao": "https://dadosabertos.camara.leg.br/api/v2/orgaos/180",
      "uriEvento": "https://dadosabertos.camara.leg.br/api/v2/eventos/79266",
      "proposicaoObjeto": null,
      "uriProposicaoObjeto": null,
      "descricao": "Rejeitado o Requerimento. Sim: 132; Não: 309; Total: 441.",
      "aprovacao": 0
    },
    {
      "id": "2270800-165",
      "uri": "https://dadosabertos.camara.leg.br/api/v2/votacoes/2270800-165",
      "data": "2025-09-16",
      "dataHoraRegistro": "2025-09-17T00:19:01",
      "siglaOrgao": "PLEN",
      "uriOrgao": "https://dadosabertos.camara.leg.br/api/v2/orgaos/180",
      "uriEvento": "https://dadosabertos.camara.leg.br/api/v2/eventos/79236",
      "proposicaoObjeto": null,
      "uriProposicaoObjeto": null,
      "descricao": "Suprimido o texto. Sim: 296; Não: 174; Total: 470.",
      "aprovacao": null
    },
    {
      "id": "2270800-160",
      "uri": "https://dadosabertos.camara.leg.br/api/v2/votacoes/2270800-160",
      "data": "2025-09-16",
      "dataHoraRegistro": "2025-09-16T23:27:10",
      "siglaOrgao": "PLEN",
      "uriOrgao": "https://dadosabertos.camara.leg.br/api/v2/orgaos/180",
      "uriEvento": "https://dadosabertos.camara.leg.br/api/v2/eventos/79236",
      "proposicaoObjeto": null,
      "uriProposicaoObjeto": null,
      "descricao": "Aprovada, em segundo turno, a Proposta de Emenda à Constituição n° 3, de 2021, ressalvado os destaques. Sim: 344; Não: 133; Total: 477.",
      "aprovacao": 1
    },
    {
      "id": "2270800-155",
      "uri": "https://dadosabertos.camara.leg.br/api/v2/votacoes/2270800-155",
      "data": "2025-09-16",
      "dataHoraRegistro": "2025-09-16T22:20:33",
      "siglaOrgao": "PLEN",
      "uriOrgao": "https://dadosabertos.camara.leg.br/api/v2/orgaos/180",
      "uriEvento": "https://dadosabertos.camara.leg.br/api/v2/eventos/79236",
      "proposicaoObjeto": null,
      "uriProposicaoObjeto": null,
      "descricao": "Aprovado o Requerimento nº 3.818/2025, dos Senhores Líderes, que solicita a quebra de interstício de 5 sessões previsto no § 6º do art. 202 do RICD, para apreciação do segundo turno da PEC 3, de 2021. Sim: 332; Não: 117; Total: 449.",
      "aprovacao": 1
    },
    {
      "id": "2270800-151",
      "uri": "https://dadosabertos.camara.leg.br/api/v2/votacoes/2270800-151",
      "data": "2025-09-16",
      "dataHoraRegistro": "2025-09-16T22:06:30",
      "siglaOrgao": "PLEN",
      "uriOrgao": "https://dadosabertos.camara.leg.br/api/v2/orgaos/180",
      "uriEvento": "https://dadosabertos.camara.leg.br/api/v2/eventos/79236",
      "proposicaoObjeto": null,
      "uriProposicaoObjeto": null,
      "descricao": "Mantido o texto. Sim: 317; Não: 156; Abstenção: 1; Total: 474.",
      "aprovacao": null
    },
    {
      "id": "2270800-148",
      "uri": "https://dadosabertos.camara.leg.br/api/v2/votacoes/2270800-148",
      "data": "2025-09-16",
      "dataHoraRegistro": "2025-09-16T21:34:12",
      "siglaOrgao": "PLEN",
      "uriOrgao": "https://dadosabertos.camara.leg.br/api/v2/orgaos/180",
      "uriEvento": "https://dadosabertos.camara.leg.br/api/v2/eventos/79236",
      "proposicaoObjeto": null,
      "uriProposicaoObjeto": null,
      "descricao": "Mantido o texto. Sim: 322; Não: 147; Abstenção: 1; Total: 470.",
      "aprovacao": null
    },
    {
      "id": "2270800-135",
      "uri": "https://dadosabertos.camara.leg.br/api/v2/votacoes/2270800-135",
      "data": "2025-09-16",
      "dataHoraRegistro": "2025-09-16T21:04:35",
      "siglaOrgao": "PLEN",
      "uriOrgao": "https://dadosabertos.camara.leg.br/api/v2/orgaos/180",
      "uriEvento": "https://dadosabertos.camara.leg.br/api/v2/eventos/79236",
      "proposicaoObjeto": null,
      "uriProposicaoObjeto": null,
      "descricao": "Aprovado, em primeiro turno, o Substitutivo Reformulado à Proposta de Emenda à Constituição nº 3, de 2021, adotado pelo Relator da Comissão Especial. Sim: 353; Não: 134; Abstenção: 1; Total: 488.",
      "aprovacao": 1
    },
    {
      "id": "2270800-130",
      "uri": "https://dadosabertos.camara.leg.br/api/v2/votacoes/2270800-130",
      "data": "2025-09-16",
      "dataHoraRegistro": "2025-09-16T20:21:40",
      "siglaOrgao": "PLEN",
      "uriOrgao": "https://dadosabertos.camara.leg.br/api/v2/orgaos/180",
      "uriEvento": "https://dadosabertos.camara.leg.br/api/v2/eventos/79236",
      "proposicaoObjeto": null,
      "uriProposicaoObjeto": null,
      "descricao": "Aprovado o Requerimento. Sim: 346; Não: 122; Total: 468.",
      "aprovacao": 1
    },
    {
      "id": "2270800-126",
      "uri": "https://dadosabertos.camara.leg.br/api/v2/votacoes/2270800-126",
      "data": "2025-09-16",
      "dataHoraRegistro": "2025-09-16T18:13:28",
      "siglaOrgao": "PLEN",
      "uriOrgao": "https://dadosabertos.camara.leg.br/api/v2/orgaos/180",
      "uriEvento": "https://dadosabertos.camara.leg.br/api/v2/eventos/79236",
      "proposicaoObjeto": null,
      "uriProposicaoObjeto": null,
      "descricao": "Rejeitado o Requerimento. Sim: 137; Não: 324; Total: 461.",
      "aprovacao": 0
    },
    {
      "id": "2270800-121",
      "uri": "https://dadosabertos.camara.leg.br/api/v2/votacoes/2270800-121",
      "data": "2025-09-16",
      "dataHoraRegistro": "2025-09-16T16:47:08",
      "siglaOrgao": "PLEN",
      "uriOrgao": "https://dadosabertos.camara.leg.br/api/v2/orgaos/180",
      "uriEvento": "https://dadosabertos.camara.leg.br/api/v2/eventos/79236",
      "proposicaoObjeto": null,
      "uriProposicaoObjeto": null,
      "descricao": "Rejeitado o Requerimento. Sim: 144; Não: 266; Total: 410.",
      "aprovacao": 0
    },
    {
      "id": "2270800-88",
      "uri": "https://dadosabertos.camara.leg.br/api/v2/votacoes/2270800-88",
      "data": "2021-02-26",
      "dataHoraRegistro": "2021-02-26T15:20:56",
      "siglaOrgao": "PLEN",
      "uriOrgao": "https://dadosabertos.camara.leg.br/api/v2/orgaos/180",
      "uriEvento": "https://dadosabertos.camara.leg.br/api/v2/eventos/60446",
      "proposicaoObjeto": null,
      "uriProposicaoObjeto": null,
      "descricao": "Rejeitado o Requerimento. Sim: 178; não: 302; abstenções: 3; total: 483.",
      "aprovacao": 0
    },
    {
      "id": "2270800-75",
      "uri": "https://dadosabertos.camara.leg.br/api/v2/votacoes/2270800-75",
      "data": "2021-02-25",
      "dataHoraRegistro": "2021-02-25T22:20:44",
      "siglaOrgao": "PLEN",
      "uriOrgao": "https://dadosabertos.camara.leg.br/api/v2/orgaos/180",
      "uriEvento": "https://dadosabertos.camara.leg.br/api/v2/eventos/60432",
      "proposicaoObjeto": null,
      "uriProposicaoObjeto": null,
      "descricao": "Rejeitada a admissibilidade dos destaques simples: Sim: 146; não: 319; abstenção: 4; total; 469.",
      "aprovacao": 0
    },
    {
      "id": "2270800-71",
      "uri": "https://dadosabertos.camara.leg.br/api/v2/votacoes/2270800-71",
      "data": "2021-02-25",
      "dataHoraRegistro": "2021-02-25T21:01:11",
      "siglaOrgao": "PLEN",
      "uriOrgao": "https://dadosabertos.camara.leg.br/api/v2/orgaos/180",
      "uriEvento": "https://dadosabertos.camara.leg.br/api/v2/eventos/60432",
      "proposicaoObjeto": null,
      "uriProposicaoObjeto": null,
      "descricao": "Aprovado o Requerimento. Sim: 310; não: 127; abstenção: 5; total: 442.",
      "aprovacao": 1
    },
    {
      "id": "2270800-68",
      "uri": "https://dadosabertos.camara.leg.br/api/v2/votacoes/2270800-68",
      "data": "2021-02-25",
      "dataHoraRegistro": "2021-02-25T20:16:45",
      "siglaOrgao": "PLEN",
      "uriOrgao": "https://dadosabertos.camara.leg.br/api/v2/orgaos/180",
      "uriEvento": "https://dadosabertos.camara.leg.br/api/v2/eventos/60432",
      "proposicaoObjeto": null,
      "uriProposicaoObjeto": null,
      "descricao": "Rejeitado o Requerimento. Sim: 150; não: 311; abstenção: 2; total: 463.",
      "aprovacao": 0
    },
    {
      "id": "2270800-62",
      "uri": "https://dadosabertos.camara.leg.br/api/v2/votacoes/2270800-62",
      "data": "2021-02-25",
      "dataHoraRegistro": "2021-02-25T19:44:38",
      "siglaOrgao": "PLEN",
      "uriOrgao": "https://dadosabertos.camara.leg.br/api/v2/orgaos/180",
      "uriEvento": "https://dadosabertos.camara.leg.br/api/v2/eventos/60432",
      "proposicaoObjeto": null,
      "uriProposicaoObjeto": null,
      "descricao": "Rejeitado o Requerimento. Sim: 149; não: 307; abstenção: 1; total: 457.",
      "aprovacao": 0
    },
    {
      "id": "2270800-61",
      "uri": "https://dadosabertos.camara.leg.br/api/v2/votacoes/2270800-61",
      "data": "2021-02-25",
      "dataHoraRegistro": "2021-02-25T19:19:56",
      "siglaOrgao": "PLEN",
      "uriOrgao": "https://dadosabertos.camara.leg.br/api/v2/orgaos/180",
      "uriEvento": "https://dadosabertos.camara.leg.br/api/v2/eventos/60432",
      "proposicaoObjeto": null,
      "uriProposicaoObjeto": null,
      "descricao": "Aprovado o Requerimento. Sim: 305; não: 151; abstenção: 1; total: 457.",
      "aprovacao": 1
    },
    {
      "id": "2270800-54",
      "uri": "https://dadosabertos.camara.leg.br/api/v2/votacoes/2270800-54",
      "data": "2021-02-25",
      "dataHoraRegistro": "2021-02-25T17:44:37",
      "siglaOrgao": "PLEN",
      "uriOrgao": "https://dadosabertos.camara.leg.br/api/v2/orgaos/180",
      "uriEvento": "https://dadosabertos.camara.leg.br/api/v2/eventos/60432",
      "proposicaoObjeto": null,
      "uriProposicaoObjeto": null,
      "descricao": "Rejeitado o Requerimento.",
      "aprovacao": 0
    },
    {
      "id": "2270800-53",
      "uri": "https://dadosabertos.camara.leg.br/api/v2/votacoes/2270800-53",
      "data": "2021-02-25",
      "dataHoraRegistro": "2021-02-25T17:38:44",
      "siglaOrgao": "PLEN",
      "uriOrgao": "https://dadosabertos.camara.leg.br/api/v2/orgaos/180",
      "uriEvento": "https://dadosabertos.camara.leg.br/api/v2/eventos/60432",
      "proposicaoObjeto": null,
      "uriProposicaoObjeto": null,
      "descricao": "Rejeitado o Requerimento. Sim: 161; não: 296; abstenção: 2; total: 459.",
      "aprovacao": 0
    },
    {
      "id": "2270800-40",
      "uri": "https://dadosabertos.camara.leg.br/api/v2/votacoes/2270800-40",
      "data": "2021-02-25",
      "dataHoraRegistro": "2021-02-25T16:54:43",
      "siglaOrgao": "PLEN",
      "uriOrgao": "https://dadosabertos.camara.leg.br/api/v2/orgaos/180",
      "uriEvento": "https://dadosabertos.camara.leg.br/api/v2/eventos/60432",
      "proposicaoObjeto": null,
      "uriProposicaoObjeto": null,
      "descricao": "Rejeitado o Requerimento. Sim: 136; não: 237; abstenção: 2; total: 375.",
      "aprovacao": 0
    },
    {
      "id": "2270800-34",
      "uri": "https://dadosabertos.camara.leg.br/api/v2/votacoes/2270800-34",
      "data": "2021-02-24",
      "dataHoraRegistro": "2021-02-24T22:26:18",
      "siglaOrgao": "PLEN",
      "uriOrgao": "https://dadosabertos.camara.leg.br/api/v2/orgaos/180",
      "uriEvento": "https://dadosabertos.camara.leg.br/api/v2/eventos/60429",
      "proposicaoObjeto": null,
      "uriProposicaoObjeto": null,
      "descricao": "Aprovado o Parecer adotado pelo Relator da Comissão de Constituição e Justiça e de Cidadania pela admissibilidade da Proposta de Emenda à Constituição nº 3, de 2021. Sim: 304; não: 154; abstenção: 2; total: 460.",
      "aprovacao": 1
    },
    {
      "id": "2270800-26",
      "uri": "https://dadosabertos.camara.leg.br/api/v2/votacoes/2270800-26",
      "data": "2021-02-24",
      "dataHoraRegistro": "2021-02-24T20:48:59",
      "siglaOrgao": "PLEN",
      "uriOrgao": "https://dadosabertos.camara.leg.br/api/v2/orgaos/180",
      "uriEvento": "https://dadosabertos.camara.leg.br/api/v2/eventos/60429",
      "proposicaoObjeto": null,
      "uriProposicaoObjeto": null,
      "descricao": "Rejeitado o Requerimento. Sim: 108; não: 363; abstenção: 5; total: 476.",
      "aprovacao": 0
    },
    {
      "id": "2270800-21",
      "uri": "https://dadosabertos.camara.leg.br/api/v2/votacoes/2270800-21",
      "data": "2021-02-24",
      "dataHoraRegistro": "2021-02-24T19:52:12",
      "siglaOrgao": "PLEN",
      "uriOrgao": "https://dadosabertos.camara.leg.br/api/v2/orgaos/180",
      "uriEvento": "https://dadosabertos.camara.leg.br/api/v2/eventos/60429",
      "proposicaoObjeto": null,
      "uriProposicaoObjeto": null,
      "descricao": "Rejeitado o Requerimento. Sim: 114; não: 373; abstenção: 2; total: 489.",
      "aprovacao": 0
    }
  ],
  "2196833": [
    {
      "id": "2196833-397",
      "uri": "https://dadosabertos.camara.leg.br/api/v2/votacoes/2196833-397",
      "data": "2023-07-07",
      "dataHoraRegistro": "2023-07-07T14:57:42",
      "siglaOrgao": "PLEN",
      "uriOrgao": "https://dadosabertos.camara.leg.br/api/v2/orgaos/180",
      "uriEvento": "https://dadosabertos.camara.leg.br/api/v2/eventos/68889",
      "proposicaoObjeto": null,
      "uriProposicaoObjeto": null,
      "descricao": "Aprovada a Redação Final assinada pelo Relator, Dep. Aguinaldo Ribeiro (PP-PB).",
      "aprovacao": 1
    },
    {
      "id": "2196833-395",
      "uri": "https://dadosabertos.camara.leg.br/api/v2/votacoes/2196833-395",
      "data": "2023-07-07",
      "dataHoraRegistro": "2023-07-07T14:56:23",
      "siglaOrgao": "PLEN",
      "uriOrgao": "https://dadosabertos.camara.leg.br/api/v2/orgaos/180",
      "uriEvento": "https://dadosabertos.camara.leg.br/api/v2/eventos/68889",
      "proposicaoObjeto": null,
      "uriProposicaoObjeto": null,
      "descricao": "Suprimido o texto. Sim: 307; não: 166; abstenção: 5; total: 478.",
      "aprovacao": null
    },
    {
      "id": "2196833-392",
      "uri": "https://dadosabertos.camara.leg.br/api/v2/votacoes/2196833-392",
      "data": "2023-07-07",
      "dataHoraRegistro": "2023-07-07T14:28:53",
      "siglaOrgao": "PLEN",
      "uriOrgao": "https://dadosabertos.camara.leg.br/api/v2/orgaos/180",
      "uriEvento": "https://dadosabertos.camara.leg.br/api/v2/eventos/68889",
      "proposicaoObjeto": null,
      "uriProposicaoObjeto": null,
      "descricao": "Mantido o texto. Sim: 370; não: 28; abstenção: 3; total: 401.",
      "aprovacao": null
    },
    {
      "id": "2196833-390",
      "uri": "https://dadosabertos.camara.leg.br/api/v2/votacoes/2196833-390",
      "data": "2023-07-07",
      "dataHoraRegistro": "2023-07-07T14:15:09",
      "siglaOrgao": "PLEN",
      "uriOrgao": "https://dadosabertos.camara.leg.br/api/v2/orgaos/180",
      "uriEvento": "https://dadosabertos.camara.leg.br/api/v2/eventos/68889",
      "proposicaoObjeto": null,
      "uriProposicaoObjeto": null,
      "descricao": "Mantido o texto. Sim: 349; não: 84; abstenção: 2; total: 435.",
      "aprovacao": null
    },
    {
      "id": "2196833-386",
      "uri": "https://dadosabertos.camara.leg.br/api/v2/votacoes/2196833-386",
      "data": "2023-07-07",
      "dataHoraRegistro": "2023-07-07T13:45:56",
      "siglaOrgao": "PLEN",
      "uriOrgao": "https://dadosabertos.camara.leg.br/api/v2/orgaos/180",
      "uriEvento": "https://dadosabertos.camara.leg.br/api/v2/eventos/68889",
      "proposicaoObjeto": null,
      "uriProposicaoObjeto": null,
      "descricao": "Mantido o texto. Sim: 336; não: 132; total: 468.",
      "aprovacao": null
    },
    {
      "id": "2196833-380",
      "uri": "https://dadosabertos.camara.leg.br/api/v2/votacoes/2196833-380",
      "data": "2023-07-06",
      "dataHoraRegistro": "2023-07-07T01:53:40",
      "siglaOrgao": "PLEN",
      "uriOrgao": "https://dadosabertos.camara.leg.br/api/v2/orgaos/180",
      "uriEvento": "https://dadosabertos.camara.leg.br/api/v2/eventos/68884",
      "proposicaoObjeto": null,
      "uriProposicaoObjeto": null,
      "descricao": "Mantido o texto. Sim: 423; não: 37; abstenção: 1; total: 461.",
      "aprovacao": null
    },
    {
      "id": "2196833-373",
      "uri": "https://dadosabertos.camara.leg.br/api/v2/votacoes/2196833-373",
      "data": "2023-07-06",
      "dataHoraRegistro": "2023-07-07T01:39:35",
      "siglaOrgao": "PLEN",
      "uriOrgao": "https://dadosabertos.camara.leg.br/api/v2/orgaos/180",
      "uriEvento": "https://dadosabertos.camara.leg.br/api/v2/eventos/68884",
      "proposicaoObjeto": null,
      "uriProposicaoObjeto": null,
      "descricao": "Aprovada, em segundo turno, a Proposta de Emenda à Constituição nº 45, de 2019, ressalvados os destaques. Sim: 375; não: 113; abstenção:3; total: 491.",
      "aprovacao": 1
    },
    {
      "id": "2196833-368",
      "uri": "https://dadosabertos.camara.leg.br/api/v2/votacoes/2196833-368",
      "data": "2023-07-06",
      "dataHoraRegistro": "2023-07-07T00:52:47",
      "siglaOrgao": "PLEN",
      "uriOrgao": "https://dadosabertos.camara.leg.br/api/v2/orgaos/180",
      "uriEvento": "https://dadosabertos.camara.leg.br/api/v2/eventos/68884",
      "proposicaoObjeto": null,
      "uriProposicaoObjeto": null,
      "descricao": "Aprovado o Requerimento nº 2.150/2023, dos Senhores Líderes, que solicita a quebra de interstício de 5 sessões previsto no § 6º do art. 202 do RICD, para apreciação do segundo turno da PEC 45, de 2019. Sim: 335; não: 100; abstenção: 2; total: 437.",
      "aprovacao": 1
    },
    {
      "id": "2196833-365",
      "uri": "https://dadosabertos.camara.leg.br/api/v2/votacoes/2196833-365",
      "data": "2023-07-06",
      "dataHoraRegistro": "2023-07-07T00:44:14",
      "siglaOrgao": "PLEN",
      "uriOrgao": "https://dadosabertos.camara.leg.br/api/v2/orgaos/180",
      "uriEvento": "https://dadosabertos.camara.leg.br/api/v2/eventos/68884",
      "proposicaoObjeto": null,
      "uriProposicaoObjeto": null,
      "descricao": "Mantido o texto. Sim: 461; não: 24; abstenção: 2; total: 487.",
      "aprovacao": null
    },
    {
      "id": "2196833-362",
      "uri": "https://dadosabertos.camara.leg.br/api/v2/votacoes/2196833-362",
      "data": "2023-07-06",
      "dataHoraRegistro": "2023-07-07T00:26:11",
      "siglaOrgao": "PLEN",
      "uriOrgao": "https://dadosabertos.camara.leg.br/api/v2/orgaos/180",
      "uriEvento": "https://dadosabertos.camara.leg.br/api/v2/eventos/68884",
      "proposicaoObjeto": null,
      "uriProposicaoObjeto": null,
      "descricao": "Mantido o texto. Sim: 344; não: 147; abstenção: 2; total: 493.",
      "aprovacao": null
    },
    {
      "id": "2196833-359",
      "uri": "https://dadosabertos.camara.leg.br/api/v2/votacoes/2196833-359",
      "data": "2023-07-06",
      "dataHoraRegistro": "2023-07-07T00:03:55",
      "siglaOrgao": "PLEN",
      "uriOrgao": "https://dadosabertos.camara.leg.br/api/v2/orgaos/180",
      "uriEvento": "https://dadosabertos.camara.leg.br/api/v2/eventos/68884",
      "proposicaoObjeto": null,
      "uriProposicaoObjeto": null,
      "descricao": "Mantido o texto. Sim: 379; não: 114; abstenção: 2; total: 495.",
      "aprovacao": null
    },
    {
      "id": "2196833-356",
      "uri": "https://dadosabertos.camara.leg.br/api/v2/votacoes/2196833-356",
      "data": "2023-07-06",
      "dataHoraRegistro": "2023-07-06T23:42:44",
      "siglaOrgao": "PLEN",
      "uriOrgao": "https://dadosabertos.camara.leg.br/api/v2/orgaos/180",
      "uriEvento": "https://dadosabertos.camara.leg.br/api/v2/eventos/68884",
      "proposicaoObjeto": null,
      "uriProposicaoObjeto": null,
      "descricao": "Mantido o texto. Sim: 383; não: 103; abstenção: 2; total: 488.",
      "aprovacao": null
    },
    {
      "id": "2196833-353",
      "uri": "https://dadosabertos.camara.leg.br/api/v2/votacoes/2196833-353",
      "data": "2023-07-06",
      "dataHoraRegistro": "2023-07-06T23:31:03",
      "siglaOrgao": "PLEN",
      "uriOrgao": "https://dadosabertos.camara.leg.br/api/v2/orgaos/180",
      "uriEvento": "https://dadosabertos.camara.leg.br/api/v2/eventos/68884",
      "proposicaoObjeto": null,
      "uriProposicaoObjeto": null,
      "descricao": "Mantido o texto. Sim: 379; não: 116; abstenção: 1; total: 496.",
      "aprovacao": null
    },
    {
      "id": "2196833-349",
      "uri": "https://dadosabertos.camara.leg.br/api/v2/votacoes/2196833-349",
      "data": "2023-07-06",
      "dataHoraRegistro": "2023-07-06T23:12:58",
      "siglaOrgao": "PLEN",
      "uriOrgao": "https://dadosabertos.camara.leg.br/api/v2/orgaos/180",
      "uriEvento": "https://dadosabertos.camara.leg.br/api/v2/eventos/68884",
      "proposicaoObjeto": null,
      "uriProposicaoObjeto": null,
      "descricao": "Mantido o texto. Sim: 390; não: 108; abstenção: 1; total: 499.",
      "aprovacao": null
    },
    {
      "id": "2196833-331",
      "uri": "https://dadosabertos.camara.leg.br/api/v2/votacoes/2196833-331",
      "data": "2023-07-06",
      "dataHoraRegistro": "2023-07-06T22:55:57",
      "siglaOrgao": "PLEN",
      "uriOrgao": "https://dadosabertos.camara.leg.br/api/v2/orgaos/180",
      "uriEvento": "https://dadosabertos.camara.leg.br/api/v2/eventos/68884",
      "proposicaoObjeto": null,
      "uriProposicaoObjeto": null,
      "descricao": "Mantido o texto. Sim: 317; não: 170; total: 487.",
      "aprovacao": null
    },
    {
      "id": "2196833-328",
      "uri": "https://dadosabertos.camara.leg.br/api/v2/votacoes/2196833-328",
      "data": "2023-07-06",
      "dataHoraRegistro": "2023-07-06T22:39:57",
      "siglaOrgao": "PLEN",
      "uriOrgao": "https://dadosabertos.camara.leg.br/api/v2/orgaos/180",
      "uriEvento": "https://dadosabertos.camara.leg.br/api/v2/eventos/68884",
      "proposicaoObjeto": null,
      "uriProposicaoObjeto": null,
      "descricao": "Aprovada a Emenda Aglutinativa nº 1. Sim: 379; não: 114; abstenção: 1; total: 494.",
      "aprovacao": 1
    },
    {
      "id": "2196833-326",
      "uri": "https://dadosabertos.camara.leg.br/api/v2/votacoes/2196833-326",
      "data": "2023-07-06",
      "dataHoraRegistro": "2023-07-06T21:49:55",
      "siglaOrgao": "PLEN",
      "uriOrgao": "https://dadosabertos.camara.leg.br/api/v2/orgaos/180",
      "uriEvento": "https://dadosabertos.camara.leg.br/api/v2/eventos/68884",
      "proposicaoObjeto": null,
      "uriProposicaoObjeto": null,
      "descricao": "Aprovado, em primeiro turno, o Substitutivo adotado pelo relator da Comissão Especial à Proposta de Emenda Constitucional nº 45, de 2019, ressalvados os destaques. Sim: 382; não: 118; abstenção: 3; total: 503.",
      "aprovacao": 1
    },
    {
      "id": "2196833-323",
      "uri": "https://dadosabertos.camara.leg.br/api/v2/votacoes/2196833-323",
      "data": "2023-07-06",
      "dataHoraRegistro": "2023-07-06T20:14:31",
      "siglaOrgao": "PLEN",
      "uriOrgao": "https://dadosabertos.camara.leg.br/api/v2/orgaos/180",
      "uriEvento": "https://dadosabertos.camara.leg.br/api/v2/eventos/68884",
      "proposicaoObjeto": null,
      "uriProposicaoObjeto": null,
      "descricao": "Rejeitado o Requerimento. Sim: 133; não: 357; abstenção: 3; total: 493.",
      "aprovacao": 0
    },
    {
      "id": "2196833-312",
      "uri": "https://dadosabertos.camara.leg.br/api/v2/votacoes/2196833-312",
      "data": "2023-07-05",
      "dataHoraRegistro": "2023-07-05T23:25:48",
      "siglaOrgao": "PLEN",
      "uriOrgao": "https://dadosabertos.camara.leg.br/api/v2/orgaos/180",
      "uriEvento": "https://dadosabertos.camara.leg.br/api/v2/eventos/68872",
      "proposicaoObjeto": null,
      "uriProposicaoObjeto": null,
      "descricao": "Rejeitado o Requerimento.",
      "aprovacao": 0
    },
    {
      "id": "2196833-307",
      "uri": "https://dadosabertos.camara.leg.br/api/v2/votacoes/2196833-307",
      "data": "2023-07-05",
      "dataHoraRegistro": "2023-07-05T21:16:25",
      "siglaOrgao": "PLEN",
      "uriOrgao": "https://dadosabertos.camara.leg.br/api/v2/orgaos/180",
      "uriEvento": "https://dadosabertos.camara.leg.br/api/v2/eventos/68872",
      "proposicaoObjeto": null,
      "uriProposicaoObjeto": null,
      "descricao": "Rejeitado o Requerimento. Sim: 148; não: 302; abstenção: 1; total: 451.",
      "aprovacao": 0
    },
    {
      "id": "2196833-88",
      "uri": "https://dadosabertos.camara.leg.br/api/v2/votacoes/2196833-88",
      "data": "2019-08-13",
      "dataHoraRegistro": "2019-08-13T15:31:32",
      "siglaOrgao": "PEC04519",
      "uriOrgao": "https://dadosabertos.camara.leg.br/api/v2/orgaos/538606",
      "uriEvento": null,
      "proposicaoObjeto": null,
      "uriProposicaoObjeto": null,
      "descricao": "Aprovado requerimento n. 1/2019 do Sr. Marlon Santos que requer a realização de Audiência Pública para discutir a PEC 45 de 2019, com a participação dos seguintes convidados: ANFIP - Associação Nacional dos Auditores Fiscais da Receita Federal do Brasil, Sr. Floriano de Sá Neto  - Presidente; FEBRAFITE  - Federação Brasileira de Associações de Fiscais de Tributos Estaduais, Sr. Juracy Braga Soares Júnior  - Presidente; FENAFISCO - Federação Nacional do Fisco Estadual e Distrital - Sr. Charles Alcantara; FENAFIM - Federação Nacional dos Auditores e Fiscais de Tributos Municipais - Sr. Célio Fernando de Souza Silva - Presidente.",
      "aprovacao": 1
    },
    {
      "id": "2196833-51",
      "uri": "https://dadosabertos.camara.leg.br/api/v2/votacoes/2196833-51",
      "data": "2019-05-22",
      "dataHoraRegistro": "2019-05-22T15:43:34",
      "siglaOrgao": "CCJC",
      "uriOrgao": "https://dadosabertos.camara.leg.br/api/v2/orgaos/2003",
      "uriEvento": "https://dadosabertos.camara.leg.br/api/v2/eventos/55658",
      "proposicaoObjeto": null,
      "uriProposicaoObjeto": null,
      "descricao": "Aprovado o Parecer contra o voto do Deputado Ivan Valente, apresentou voto em separado a Deputada Talíria Petrone.",
      "aprovacao": 1
    }
  ],
  "2122076": [
    {
      "id": "2122076-411",
      "uri": "https://dadosabertos.camara.leg.br/api/v2/votacoes/2122076-411",
      "data": "2017-04-26",
      "dataHoraRegistro": "2017-04-27T02:24:57",
      "siglaOrgao": "PLEN",
      "uriOrgao": "https://dadosabertos.camara.leg.br/api/v2/orgaos/180",
      "uriEvento": "https://dadosabertos.camara.leg.br/api/v2/eventos/47151",
      "proposicaoObjeto": null,
      "uriProposicaoObjeto": null,
      "descricao": "Aprovada a Redação Final assinada pelo Relator, Dep. Rogério Marinho (PSDB-RN).",
      "aprovacao": 1
    },
    {
      "id": "2122076-391",
      "uri": "https://dadosabertos.camara.leg.br/api/v2/votacoes/2122076-391",
      "data": "2017-04-26",
      "dataHoraRegistro": "2017-04-27T02:06:46",
      "siglaOrgao": "PLEN",
      "uriOrgao": "https://dadosabertos.camara.leg.br/api/v2/orgaos/180",
      "uriEvento": "https://dadosabertos.camara.leg.br/api/v2/eventos/47151",
      "proposicaoObjeto": null,
      "uriProposicaoObjeto": null,
      "descricao": "Rejeitada a Emenda. Sim: 159; não: 259; abstenção: 5; total: 423.",
      "aprovacao": 0
    },
    {
      "id": "2122076-387",
      "uri": "https://dadosabertos.camara.leg.br/api/v2/votacoes/2122076-387",
      "data": "2017-04-26",
      "dataHoraRegistro": "2017-04-27T01:28:49",
      "siglaOrgao": "PLEN",
      "uriOrgao": "https://dadosabertos.camara.leg.br/api/v2/orgaos/180",
      "uriEvento": "https://dadosabertos.camara.leg.br/api/v2/eventos/47151",
      "proposicaoObjeto": null,
      "uriProposicaoObjeto": null,
      "descricao": "Rejeitada a Emenda de Plenário n°15. Sim: 133; não: 285; abstenção: 4; total: 422.",
      "aprovacao": 0
    },
    {
      "id": "2122076-384",
      "uri": "https://dadosabertos.camara.leg.br/api/v2/votacoes/2122076-384",
      "data": "2017-04-26",
      "dataHoraRegistro": "2017-04-27T01:06:07",
      "siglaOrgao": "PLEN",
      "uriOrgao": "https://dadosabertos.camara.leg.br/api/v2/orgaos/180",
      "uriEvento": "https://dadosabertos.camara.leg.br/api/v2/eventos/47151",
      "proposicaoObjeto": null,
      "uriProposicaoObjeto": null,
      "descricao": "Mantido o texto.",
      "aprovacao": 1
    },
    {
      "id": "2122076-382",
      "uri": "https://dadosabertos.camara.leg.br/api/v2/votacoes/2122076-382",
      "data": "2017-04-26",
      "dataHoraRegistro": "2017-04-27T00:57:50",
      "siglaOrgao": "PLEN",
      "uriOrgao": "https://dadosabertos.camara.leg.br/api/v2/orgaos/180",
      "uriEvento": "https://dadosabertos.camara.leg.br/api/v2/eventos/47151",
      "proposicaoObjeto": null,
      "uriProposicaoObjeto": null,
      "descricao": "Aprovada a Emenda de Plenário n° 16.",
      "aprovacao": 1
    },
    {
      "id": "2122076-378",
      "uri": "https://dadosabertos.camara.leg.br/api/v2/votacoes/2122076-378",
      "data": "2017-04-26",
      "dataHoraRegistro": "2017-04-27T00:50:19",
      "siglaOrgao": "PLEN",
      "uriOrgao": "https://dadosabertos.camara.leg.br/api/v2/orgaos/180",
      "uriEvento": "https://dadosabertos.camara.leg.br/api/v2/eventos/47151",
      "proposicaoObjeto": null,
      "uriProposicaoObjeto": null,
      "descricao": "Mantido o texto.",
      "aprovacao": 1
    },
    {
      "id": "2122076-375",
      "uri": "https://dadosabertos.camara.leg.br/api/v2/votacoes/2122076-375",
      "data": "2017-04-26",
      "dataHoraRegistro": "2017-04-27T00:37:25",
      "siglaOrgao": "PLEN",
      "uriOrgao": "https://dadosabertos.camara.leg.br/api/v2/orgaos/180",
      "uriEvento": "https://dadosabertos.camara.leg.br/api/v2/eventos/47151",
      "proposicaoObjeto": null,
      "uriProposicaoObjeto": null,
      "descricao": "Mantido o texto.",
      "aprovacao": 1
    },
    {
      "id": "2122076-371",
      "uri": "https://dadosabertos.camara.leg.br/api/v2/votacoes/2122076-371",
      "data": "2017-04-26",
      "dataHoraRegistro": "2017-04-27T00:27:47",
      "siglaOrgao": "PLEN",
      "uriOrgao": "https://dadosabertos.camara.leg.br/api/v2/orgaos/180",
      "uriEvento": "https://dadosabertos.camara.leg.br/api/v2/eventos/47151",
      "proposicaoObjeto": null,
      "uriProposicaoObjeto": null,
      "descricao": "Mantido o texto. Sim: 274; não: 160; abstenção: 1; total: 435.",
      "aprovacao": 1
    },
    {
      "id": "2122076-366",
      "uri": "https://dadosabertos.camara.leg.br/api/v2/votacoes/2122076-366",
      "data": "2017-04-26",
      "dataHoraRegistro": "2017-04-26T23:58:03",
      "siglaOrgao": "PLEN",
      "uriOrgao": "https://dadosabertos.camara.leg.br/api/v2/orgaos/180",
      "uriEvento": "https://dadosabertos.camara.leg.br/api/v2/eventos/47151",
      "proposicaoObjeto": null,
      "uriProposicaoObjeto": null,
      "descricao": "Rejeitada a Emenda n° 13.",
      "aprovacao": 0
    },
    {
      "id": "2122076-363",
      "uri": "https://dadosabertos.camara.leg.br/api/v2/votacoes/2122076-363",
      "data": "2017-04-26",
      "dataHoraRegistro": "2017-04-26T23:51:21",
      "siglaOrgao": "PLEN",
      "uriOrgao": "https://dadosabertos.camara.leg.br/api/v2/orgaos/180",
      "uriEvento": "https://dadosabertos.camara.leg.br/api/v2/eventos/47151",
      "proposicaoObjeto": null,
      "uriProposicaoObjeto": null,
      "descricao": "Mantido texto.",
      "aprovacao": 1
    },
    {
      "id": "2122076-361",
      "uri": "https://dadosabertos.camara.leg.br/api/v2/votacoes/2122076-361",
      "data": "2017-04-26",
      "dataHoraRegistro": "2017-04-26T23:43:52",
      "siglaOrgao": "PLEN",
      "uriOrgao": "https://dadosabertos.camara.leg.br/api/v2/orgaos/180",
      "uriEvento": "https://dadosabertos.camara.leg.br/api/v2/eventos/47151",
      "proposicaoObjeto": null,
      "uriProposicaoObjeto": null,
      "descricao": "Mantido o texto.",
      "aprovacao": 1
    },
    {
      "id": "2122076-358",
      "uri": "https://dadosabertos.camara.leg.br/api/v2/votacoes/2122076-358",
      "data": "2017-04-26",
      "dataHoraRegistro": "2017-04-26T23:23:27",
      "siglaOrgao": "PLEN",
      "uriOrgao": "https://dadosabertos.camara.leg.br/api/v2/orgaos/180",
      "uriEvento": "https://dadosabertos.camara.leg.br/api/v2/eventos/47151",
      "proposicaoObjeto": null,
      "uriProposicaoObjeto": null,
      "descricao": "Mantido o texto. Sim: 258; não: 158; abstenção: 2; total: 418.",
      "aprovacao": 1
    },
    {
      "id": "2122076-348",
      "uri": "https://dadosabertos.camara.leg.br/api/v2/votacoes/2122076-348",
      "data": "2017-04-26",
      "dataHoraRegistro": "2017-04-26T22:31:11",
      "siglaOrgao": "PLEN",
      "uriOrgao": "https://dadosabertos.camara.leg.br/api/v2/orgaos/180",
      "uriEvento": "https://dadosabertos.camara.leg.br/api/v2/eventos/47140",
      "proposicaoObjeto": null,
      "uriProposicaoObjeto": null,
      "descricao": "Aprovada a Subemenda Substitutiva Global apresentada pelo Relator da Comissão Especial, ressalvados os destaques. Sim: 296; não:177; total: 473.",
      "aprovacao": 1
    },
    {
      "id": "2122076-345",
      "uri": "https://dadosabertos.camara.leg.br/api/v2/votacoes/2122076-345",
      "data": "2017-04-26",
      "dataHoraRegistro": "2017-04-26T21:34:26",
      "siglaOrgao": "PLEN",
      "uriOrgao": "https://dadosabertos.camara.leg.br/api/v2/orgaos/180",
      "uriEvento": "https://dadosabertos.camara.leg.br/api/v2/eventos/47140",
      "proposicaoObjeto": null,
      "uriProposicaoObjeto": null,
      "descricao": "Rejeitada a admissibilidade dos destaques simples. Em consequência, fica prejudicada a apreciação dos referidos destaques.",
      "aprovacao": 0
    },
    {
      "id": "2122076-343",
      "uri": "https://dadosabertos.camara.leg.br/api/v2/votacoes/2122076-343",
      "data": "2017-04-26",
      "dataHoraRegistro": "2017-04-26T21:30:25",
      "siglaOrgao": "PLEN",
      "uriOrgao": "https://dadosabertos.camara.leg.br/api/v2/orgaos/180",
      "uriEvento": "https://dadosabertos.camara.leg.br/api/v2/eventos/47140",
      "proposicaoObjeto": null,
      "uriProposicaoObjeto": null,
      "descricao": "Aprovado o Requerimento.",
      "aprovacao": 1
    },
    {
      "id": "2122076-340",
      "uri": "https://dadosabertos.camara.leg.br/api/v2/votacoes/2122076-340",
      "data": "2017-04-26",
      "dataHoraRegistro": "2017-04-26T21:14:17",
      "siglaOrgao": "PLEN",
      "uriOrgao": "https://dadosabertos.camara.leg.br/api/v2/orgaos/180",
      "uriEvento": "https://dadosabertos.camara.leg.br/api/v2/eventos/47140",
      "proposicaoObjeto": null,
      "uriProposicaoObjeto": null,
      "descricao": "Rejeitada a apreciação parcelada da matéria. Em consequência, ficam prejudicados os referidos Requerimentos.",
      "aprovacao": 0
    },
    {
      "id": "2122076-337",
      "uri": "https://dadosabertos.camara.leg.br/api/v2/votacoes/2122076-337",
      "data": "2017-04-26",
      "dataHoraRegistro": "2017-04-26T20:53:54",
      "siglaOrgao": "PLEN",
      "uriOrgao": "https://dadosabertos.camara.leg.br/api/v2/orgaos/180",
      "uriEvento": "https://dadosabertos.camara.leg.br/api/v2/eventos/47140",
      "proposicaoObjeto": null,
      "uriProposicaoObjeto": null,
      "descricao": "Rejeitado o Requerimento.",
      "aprovacao": 0
    },
    {
      "id": "2122076-334",
      "uri": "https://dadosabertos.camara.leg.br/api/v2/votacoes/2122076-334",
      "data": "2017-04-26",
      "dataHoraRegistro": "2017-04-26T20:40:31",
      "siglaOrgao": "PLEN",
      "uriOrgao": "https://dadosabertos.camara.leg.br/api/v2/orgaos/180",
      "uriEvento": "https://dadosabertos.camara.leg.br/api/v2/eventos/47140",
      "proposicaoObjeto": null,
      "uriProposicaoObjeto": null,
      "descricao": "Rejeitado o Requerimento.",
      "aprovacao": 0
    },
    {
      "id": "2122076-331",
      "uri": "https://dadosabertos.camara.leg.br/api/v2/votacoes/2122076-331",
      "data": "2017-04-26",
      "dataHoraRegistro": "2017-04-26T20:29:40",
      "siglaOrgao": "PLEN",
      "uriOrgao": "https://dadosabertos.camara.leg.br/api/v2/orgaos/180",
      "uriEvento": "https://dadosabertos.camara.leg.br/api/v2/eventos/47140",
      "proposicaoObjeto": null,
      "uriProposicaoObjeto": null,
      "descricao": "Rejeitado o Requerimento.",
      "aprovacao": 0
    },
    {
      "id": "2122076-324",
      "uri": "https://dadosabertos.camara.leg.br/api/v2/votacoes/2122076-324",
      "data": "2017-04-26",
      "dataHoraRegistro": "2017-04-26T19:58:14",
      "siglaOrgao": "PLEN",
      "uriOrgao": "https://dadosabertos.camara.leg.br/api/v2/orgaos/180",
      "uriEvento": "https://dadosabertos.camara.leg.br/api/v2/eventos/47140",
      "proposicaoObjeto": null,
      "uriProposicaoObjeto": null,
      "descricao": "Aprovado o Requerimento. Sim: 226; não: 125; abstenção: 1; total: 352.",
      "aprovacao": 1
    },
    {
      "id": "2122076-320",
      "uri": "https://dadosabertos.camara.leg.br/api/v2/votacoes/2122076-320",
      "data": "2017-04-26",
      "dataHoraRegistro": "2017-04-26T19:22:39",
      "siglaOrgao": "PLEN",
      "uriOrgao": "https://dadosabertos.camara.leg.br/api/v2/orgaos/180",
      "uriEvento": "https://dadosabertos.camara.leg.br/api/v2/eventos/47140",
      "proposicaoObjeto": null,
      "uriProposicaoObjeto": null,
      "descricao": "Rejeitado o Requerimento.",
      "aprovacao": 0
    },
    {
      "id": "2122076-316",
      "uri": "https://dadosabertos.camara.leg.br/api/v2/votacoes/2122076-316",
      "data": "2017-04-26",
      "dataHoraRegistro": "2017-04-26T18:51:28",
      "siglaOrgao": "PLEN",
      "uriOrgao": "https://dadosabertos.camara.leg.br/api/v2/orgaos/180",
      "uriEvento": "https://dadosabertos.camara.leg.br/api/v2/eventos/47140",
      "proposicaoObjeto": null,
      "uriProposicaoObjeto": null,
      "descricao": "Rejeitado o Requerimento. Sim: 64; não: 270; total: 334.",
      "aprovacao": 0
    },
    {
      "id": "2122076-304",
      "uri": "https://dadosabertos.camara.leg.br/api/v2/votacoes/2122076-304",
      "data": "2017-04-26",
      "dataHoraRegistro": "2017-04-26T14:56:11",
      "siglaOrgao": "PLEN",
      "uriOrgao": "https://dadosabertos.camara.leg.br/api/v2/orgaos/180",
      "uriEvento": "https://dadosabertos.camara.leg.br/api/v2/eventos/47128",
      "proposicaoObjeto": null,
      "uriProposicaoObjeto": null,
      "descricao": "Rejeitado o Requerimento. Sim: 45; não: 213; total: 258.",
      "aprovacao": 0
    },
    {
      "id": "2122076-298",
      "uri": "https://dadosabertos.camara.leg.br/api/v2/votacoes/2122076-298",
      "data": "2017-04-26",
      "dataHoraRegistro": "2017-04-26T13:23:21",
      "siglaOrgao": "PLEN",
      "uriOrgao": "https://dadosabertos.camara.leg.br/api/v2/orgaos/180",
      "uriEvento": "https://dadosabertos.camara.leg.br/api/v2/eventos/47120",
      "proposicaoObjeto": null,
      "uriProposicaoObjeto": null,
      "descricao": "Rejeitado o Requerimento. Sim: 49; não: 224; abstenção: 1: total: 274.",
      "aprovacao": 0
    },
    {
      "id": "2122076-293",
      "uri": "https://dadosabertos.camara.leg.br/api/v2/votacoes/2122076-293",
      "data": "2017-04-25",
      "dataHoraRegistro": "2017-04-25T19:50:51",
      "siglaOrgao": "PL678716",
      "uriOrgao": "https://dadosabertos.camara.leg.br/api/v2/orgaos/537991",
      "uriEvento": "https://dadosabertos.camara.leg.br/api/v2/eventos/47070",
      "proposicaoObjeto": null,
      "uriProposicaoObjeto": null,
      "descricao": "Aprovado o Parecer com Complementação de Voto, ressalvados os destaques. Apresentaram votos em separado os Deputados Assis Melo, Helder Salomão, Patrus Ananias, Paulão, Leonardo Monteiro, Waldenor Pereira, Benedita da Silva, Wadih Damous e Robinson Almeida.",
      "aprovacao": 1
    },
    {
      "id": "2122076-267",
      "uri": "https://dadosabertos.camara.leg.br/api/v2/votacoes/2122076-267",
      "data": "2017-03-28",
      "dataHoraRegistro": "2017-03-28T18:44:02",
      "siglaOrgao": "PL678716",
      "uriOrgao": "https://dadosabertos.camara.leg.br/api/v2/orgaos/537991",
      "uriEvento": null,
      "proposicaoObjeto": null,
      "uriProposicaoObjeto": null,
      "descricao": "Aprovado requerimento n. 113/2017 da Sra. Gorete Pereira que requer seja convidado representante da Associação Brasileira do Trabalho Temporário - ASSERTTEM, para debater o PL nº 6.787, de 2016. Nomes para participar dos debates na Comissão: Michelle Karine, Diretora de Comunicação da ASSERTTEM; Marcos Abreu, Diretor Jurídico da ASSERTTEM; Guilherme Paletta, Diretor Regional da ASSERTTEM no Rio de Janeiro; Filipe Baumgratz Delgado Mota, Procurador-jurídico da ASSERTTEM; Toni Camargo, Conselheiro Consultivo da ASSERTTEM; Alexandre de Sá Domingues, Presidente OAB - 57ª Subseção Guarulhos.",
      "aprovacao": 1
    },
    {
      "id": "2122076-266",
      "uri": "https://dadosabertos.camara.leg.br/api/v2/votacoes/2122076-266",
      "data": "2017-03-28",
      "dataHoraRegistro": "2017-03-28T15:01:29",
      "siglaOrgao": "PL678716",
      "uriOrgao": "https://dadosabertos.camara.leg.br/api/v2/orgaos/537991",
      "uriEvento": null,
      "proposicaoObjeto": null,
      "uriProposicaoObjeto": null,
      "descricao": "Aprovado requerimento n. 113/2017 da Sra. Gorete Pereira que requer seja convidado representante da Associação Brasileira do Trabalho Temporário - ASSERTTEM, para debater o PL nº 6.787, de 2016. Nomes para participar dos debates na Comissão: Michelle Karine, Diretora de Comunicação da ASSERTTEM; Marcos Abreu, Diretor Jurídico da ASSERTTEM; Guilherme Paletta, Diretor Regional da ASSERTTEM no Rio de Janeiro; Filipe Baumgratz Delgado Mota, Procurador-jurídico da ASSERTTEM; Toni Camargo, Conselheiro Consultivo da ASSERTTEM; Alexandre de Sá Domingues, Presidente OAB - 57ª Subseção Guarulhos.",
      "aprovacao": 1
    }
  ]
}